LICENSE
MANIFEST.in
README.md
requirements.txt
setup.py
lpacli/__init__.py
lpacli/config.py
lpacli/login.py
lpacli/main.py
lpacli.egg-info/PKG-INFO
lpacli.egg-info/SOURCES.txt
lpacli.egg-info/dependency_links.txt
lpacli.egg-info/entry_points.txt
lpacli.egg-info/requires.txt
lpacli.egg-info/top_level.txt
lpacli/api/__init__.py
lpacli/api/lesspassapiclient.py
lpacli/commands/__init__.py
lpacli/commands/get_pass.py