Metadata-Version: 2.1
Name: lpacli
Version: 0.1.2
Summary: CLI helper to get LessPass paswords configuration directly from a LessPass server.
Home-page: https://github.com/ogarcia/lpacli
Author: Óscar García Amor
Author-email: ogarcia@connectical.com
License: GPLv3
Project-URL: Bug Reports, https://github.com/ogarcia/lpacli/issues
Project-URL: Source, https://github.com/ogarcia/lpacli
Keywords: lesspass api client passwords
Platform: UNKNOWN
Classifier: Development Status :: 4 - Beta
Classifier: Environment :: Console
Classifier: Intended Audience :: Developers
Classifier: Intended Audience :: System Administrators
Classifier: License :: OSI Approved :: GNU General Public License v3 (GPLv3)
Classifier: Natural Language :: English
Classifier: Operating System :: OS Independent
Classifier: Programming Language :: Python :: 3
Classifier: Topic :: Utilities
